sigma/backends/kusto/__init__.py
sigma/backends/kusto/kusto.py
sigma/backends/microsoft365defender/__init__.py
sigma/backends/microsoft365defender/microsoft365defender.py
sigma/pipelines/azuremonitor/__init__.py
sigma/pipelines/azuremonitor/azuremonitor.py
sigma/pipelines/azuremonitor/mappings.py
sigma/pipelines/azuremonitor/schema.py
sigma/pipelines/azuremonitor/tables.py
sigma/pipelines/azuremonitor/transformations.py
sigma/pipelines/kusto_common/__init__.py
sigma/pipelines/kusto_common/conditions.py
sigma/pipelines/kusto_common/errors.py
sigma/pipelines/kusto_common/finalization.py
sigma/pipelines/kusto_common/mappings.py
sigma/pipelines/kusto_common/postprocessing.py
sigma/pipelines/kusto_common/schema.py
sigma/pipelines/kusto_common/transformations.py
sigma/pipelines/microsoft365defender/__init__.py
sigma/pipelines/microsoft365defender/microsoft365defender.py
sigma/pipelines/microsoftxdr/__init__.py
sigma/pipelines/microsoftxdr/mappings.py
sigma/pipelines/microsoftxdr/microsoftxdr.py
sigma/pipelines/microsoftxdr/schema.py
sigma/pipelines/microsoftxdr/tables.py
sigma/pipelines/microsoftxdr/transformations.py
sigma/pipelines/sentinelasim/__init__.py
sigma/pipelines/sentinelasim/mappings.py
sigma/pipelines/sentinelasim/schema.py
sigma/pipelines/sentinelasim/sentinelasim.py
sigma/pipelines/sentinelasim/tables.py
sigma/pipelines/sentinelasim/transformations.py
pysigma_backend_kusto-0.4.4.dist-info/LICENSE
pysigma_backend_kusto-0.4.4.dist-info/METADATA
pysigma_backend_kusto-0.4.4.dist-info/WHEEL
pysigma_backend_kusto-0.4.4.dist-info/RECORD
