Metadata-Version: 2.3
Name: pySigma-backend-kusto
Version: 0.4.4
Summary: pySigma Kusto backend
License: LGPL-3.0-only
Author: Stephen Lincoln
Author-email: stephen.lincoln@attackiq.com
Requires-Python: >=3.8,<4.0
Classifier: License :: OSI Approved :: GNU Lesser General Public License v3 (LGPLv3)
Classifier: Programming Language :: Python :: 3
Classifier: Programming Language :: Python :: 3.8
Classifier: Programming Language :: Python :: 3.9
Classifier: Programming Language :: Python :: 3.10
Classifier: Programming Language :: Python :: 3.11
Classifier: Programming Language :: Python :: 3.12
Classifier: Programming Language :: Python :: 3.13
Requires-Dist: certifi (>=2023.07.22)
Requires-Dist: pysigma (>=0.10.0)
Project-URL: Repository, https://github.com/AttackIQ/pySigma-backend-kusto
